tasklist/__init__.py
tasklist/task.py
tasklist/tasklist.py
tasklist/utils.py
tasklist-1.2.1.dist-info/METADATA
tasklist-1.2.1.dist-info/WHEEL
tasklist-1.2.1.dist-info/top_level.txt
tasklist-1.2.1.dist-info/RECORD
