Metadata-Version: 2.1
Name: tasklist
Version: 1.2.1
Summary: A library to manage lists of commands with re-trial.
Home-page: https://gitlab.com/buddyns/tasklist
Author: BuddyNS.com
Author-email: support@buddyns.com
License: UNKNOWN
Platform: UNKNOWN
Classifier: Operating System :: POSIX
Classifier: Programming Language :: Python :: 3
Classifier: Programming Language :: Python :: 2
Classifier: Development Status :: 5 - Production/Stable
Classifier: Intended Audience :: Developers
Classifier: License :: OSI Approved :: BSD License
Classifier: Topic :: Software Development
Classifier: Topic :: System
